prismatools/__init__.py
prismatools/gui.py
prismatools/prisma.py
prismatools/prismatools.py
prismatools/spatial.py
prismatools/utils.py
prismatools-0.1.4.dist-info/licenses/LICENSE
prismatools-0.1.4.dist-info/METADATA
prismatools-0.1.4.dist-info/WHEEL
prismatools-0.1.4.dist-info/entry_points.txt
prismatools-0.1.4.dist-info/top_level.txt
prismatools-0.1.4.dist-info/RECORD
