Metadata-Version: 2.4
Name: prismatools
Version: 0.1.4
Summary: prismatools is an open-source Python package for reading, analyzing, and visualizing hyperspectral imagery from the PRISMA mission.
Author-email: Lorenzo Crecco <lorenzo.crecco@hotmail.com>
License: MIT License
Project-URL: Homepage, https://github.com/gthlor/prismatools
Keywords: prismatools
Classifier: Intended Audience :: Developers
Classifier: License :: OSI Approved :: MIT License
Classifier: Natural Language :: English
Classifier: Programming Language :: Python :: 3.10
Classifier: Programming Language :: Python :: 3.11
Classifier: Programming Language :: Python :: 3.12
Requires-Python: >=3.10
License-File: LICENSE
Requires-Dist: affine
Requires-Dist: bqplot
Requires-Dist: h5py
Requires-Dist: ipyevents
Requires-Dist: ipyfilechooser
Requires-Dist: ipyleaflet
Requires-Dist: ipywidgets
Requires-Dist: leafmap
Requires-Dist: localtileserver
Requires-Dist: matplotlib
Requires-Dist: numpy
Requires-Dist: pandas
Requires-Dist: rioxarray
Requires-Dist: scikit-learn
Requires-Dist: xarray
Provides-Extra: all
Requires-Dist: prismatools[extra]; extra == "all"
Provides-Extra: extra
Requires-Dist: pandas; extra == "extra"
Dynamic: license-file
